fedem/__init__.py
fedem/client/__init__.py
fedem/configurations/__init__.py
fedem/configurations/mamba.py
fedem/models/__init__.py
fedem/models/mamba.py
fedem/server/__init__.py
fedem/trainer/__init__.py
fedem/utils/__init__.py
fedem/utils/huggingface.py
fedem-0.0.7.dist-info/LICENSE.md
fedem-0.0.7.dist-info/METADATA
fedem-0.0.7.dist-info/WHEEL
fedem-0.0.7.dist-info/top_level.txt
fedem-0.0.7.dist-info/RECORD
