Metadata-Version: 2.1
Name: fedem
Version: 0.0.7
Summary: A decentralized framework to train foundational models
Home-page: https://github.com/mlsquare/fedem
Author: MLSquare
Author-email: mail@mlsquare.com
License: MIT
Project-URL: Documentation, https://mlsquare.github.io/fedem/
Project-URL: Source, https://github.com/mlsquare/fedem/
Classifier: Development Status :: 4 - Beta
Classifier: Intended Audience :: Developers
Classifier: Programming Language :: Python :: 3.10
Classifier: License :: OSI Approved :: MIT License
Requires-Python: >=3.10
License-File: LICENSE.md
Requires-Dist: transformers
Requires-Dist: torch
Requires-Dist: datasets
Requires-Dist: einops
Requires-Dist: accelerate
Requires-Dist: peft
Requires-Dist: huggingface-hub
